{
  "GlobalStrings": {
    "INV_ITEM_FLARES": [
      "Blistavo",
      "Pomoć za flipmap",
      "Uhh Svjetleće!",
      "Poništavanje stumblea",
      "Iskoristi me!"
    ],
    "INV_ITEM_PISTOLS": [
      "Dupli pištolj",
      "Šifra za varanje",
      "Klasični klasik",
      "Ikonici",
      "Beskonačna ubojstva"
    ],
    "INV_ITEM_PISTOL_AMMO": [
      "Klipovi za pištolje",
      "Klipovi za varanje",
      "Klipovi za klasik",
      "Ikonični klipovi",
      "Klipovi za beskonačna ubojstva"
    ],
    "INV_ITEM_SHOTGUN": [
      "Sačma govno",
      "Zašto?",
      "Dođi ovdje ili ništa!",
      "Vidjeli dovoljno?",
      "Ostavi ga! Zauzet je!"
    ],
    "INV_ITEM_SHOTGUN_AMMO": [
      "Meci za sačmu",
      "Upitni meci",
      "Puževi",
      "Vidjeli dovoljno meci?",
      "Zauzeti meci"
    ],
    "INV_ITEM_DEAGLE": [
      "Vili Killy",
      "Zapravo korisno!",
      "O-rao",
      "Nevada O-rao",
      "Najbolji u loncu"
    ],
    "INV_ITEM_DEAGLE_AMMO": [
      "Willy Killy meci",
      "Korisni meci",
      "O-rao meci",
      "Orao metci",
      "Najbolji meci"
    ],
    "INV_ITEM_UZI": [
      "Vampri meci",
      "Auto 2.0",
      "Nije TR II uzi",
      "Ju-uzi",
      "Nisu jaki meci!"
    ],
    "INV_ITEM_UZI_AMMO": [
      "Vampir meci",
      "Klipovi 2.0",
      "Izgrebani meci",
      "Ju-uzi meci",
      "Slabiji meci"
    ],
    "INV_ITEM_HARPOON": [
      "Meme Pištolj",
      "Beskorisno",
      "Samo za izazove",
      "Zašto ovo postoji?",
      "Podvodni samostrel"
    ],
    "INV_ITEM_HARPOON_AMMO": [
      "Dank Meme",
      "Smeće",
      "Izazivači",
      "Egzistencijai",
      "Lukovi"
    ],
    "INV_ITEM_M16": [
      "Nije M16",
      "M16",
      "Raptor ubojica",
      "MP3 muzika",
      "Pojačivač raketi"
    ],
    "INV_ITEM_M16_AMMO": [
      "Lažni meci",
      "Prevara",
      "Raptor ubojice",
      "Staze",
      "Učativač raketi"
    ],
    "INV_ITEM_ROCKET_LAUNCHER": [
      "Ultimativni bum",
      "Turet za torbu",
      "Ionako je predugo",
      "Totalno neprecizno",
      "Veliki trzaj?"
    ],
    "INV_ITEM_ROCKETS": [
      "Ultimativne rakete",
      "Rakete za torbu",
      "Spore rakete",
      "Neprecizne rakete",
      "Teške rakete"
    ],
    "INV_ITEM_GRENADE_LAUNCHER": [
      "Neprecizne stvari",
      "Bolji lanser COPIUM",
      "Veliki bum",
      "Za što ti trebam?",
      "Nije više 7"
    ],
    "INV_ITEM_GRENADE_AMMO": [
      "Neprecizne granate",
      "COPIUM granate",
      "Veliki bum granate",
      "Upitne granate",
      "Granate na popustu"
    ],
    "INV_ITEM_MEDI": [
      "Zabranjeno korištenje!",
      "Nisi na LJEKOVIMA!",
      "Mala bolnica",
      "Mali spasitelj",
      "Kristal za torbu"
    ],
    "INV_ITEM_BIG_MEDI": [
      "Zabranjeno korištenje!",
      "Nisi na LJEKOVIMA",
      "Velika bolnica",
      "Veliki spasitelj",
      "Vreća kristala"
    ],
    "HEADING_ITEMS": [
      "Stvari",
      "Što je ovo?",
      "Nije sjajno!",
      "Smeće",
      "Ovo i ono",
      "Previše artifakta!",
      "Kako stanu?"
    ],
    "HEADING_GAME_OVER": [
      "Zakajakirali ste se?",
      "NLNMAS slijedi?",
      "MRTAV SI!",
      "Budi bolji!",
      "Zaboravili ste se healat?",
      "Prva pomoć?",
      "Stvarno ste umrijeli ovdje?"
    ],
    "INV_ITEM_COMPASS": [
      "Brojač potrošenih stvari",
      "Any% slijedi?",
      "Može li sporije?",
      "Sve tajne?",
      "Nema prve pomoći!",
      "Pacifist?"
    ],
    "INV_GLOBE_LONDON": [
      "Grad bitova",
      "Južna Engleska",
      "Je li kraljica kući?",
      "Mačji grad",
      "10 minuta do ponoći!"
    ],
    "INV_GLOBE_NEVADA": [
      "Popunjena pustinja",
      "Prašina...svuda",
      "OI!",
      "HEY!",
      "Orlova pustinja"
    ],
    "INV_GLOBE_SOUTH_PACIFIC": [
      "Voda i stvari",
      "Zaboravljeni otok",
      "Kanibalizam",
      "Punin kut",
      "Južna tuga",
      "Južna Indija"
    ],
    "INV_GLOBE_ANTARCTICA": [
      "Ogromni frižider",
      "Gdje je Winston?",
      "Hipertermija",
      "Titanik 2.0",
      "Veliki, hladni, bijeli",
      "Santa leda!"
    ],
    "MISC_EMPTY_SLOT_FMT": [
      "- NULA -",
      "- NIŠTA OVDJE -",
      "- NEDEFINIRANO -",
      "- OI, PRAZNO MJESTO -"
    ]
  },
  "LevelStrings": {
    "HOUSE.TR2": {
      "Names": [
        "Skromno prebivalište",
        "Winstonov frižider 2.0",
        "Traka za quad formule",
        "Winston... dupli?",
        "Vježba za gađanje",
        "Sretna mirovina"
      ],
      "KeyItems": {
        "Key1": [
          "Ključ za utrku",
          "Ključ zastave",
          "Formula 1 ključ",
          "Riblji ključ",
          "Ključ trofeja",
          "Pristup quadu"
        ]
      }
    },
    "JUNGLE.TR2": {
      "Names": [
        "Knjiga o džungli",
        "Rođaci kralja Luja",
        "Bodljikavo sklizanje",
        "Rollin rollin rollin",
        "Kotrljajuče kamenje"
      ],
      "KeyItems": {
        "Key4": [
          "Lijepi ključ",
          "MajMun",
          "Beskoristan ključ",
          "Glitchless ključ",
          "Što je ovo? O.o"
        ]
      }
    },
    "TEMPLE.TR2": {
      "Names": [
        "Randijeva i Rorina grobnica",
        "Zašto toliko Šiva?",
        "Kipovi otporne na metke",
        "Zmije i ljestve",
        "Zamka pakla",
        "Trik sa svijećom"
      ],
      "KeyItems": {
        "Key1": [
          "Nema dupliciranja",
          "Smrtonosni ključ",
          "5 noći Ganeše",
          "Nisu molitveni kotači",
          "Komora za mučenje"
        ]
      }
    },
    "QUADCHAS.TR2": {
      "Names": [
        "Trebaš quad?",
        "Dolina pirana",
        "Ne Temza",
        "Ne roni djevojko!",
        "Nema Barney-a!"
      ],
      "KeyItems": {
        "Key1": [
          "Dvostruko beskorisno",
          "Tko ovo skuplja?",
          "DuPli MajMun",
          "Nije ključ katedrale",
          "Što je ovo?"
        ]
      }
    },
    "TONYBOSS.TR2": {
      "Names": [
        "Odlično",
        "Još jedan labirint",
        "Tajni labirint?!? O.o",
        "40 slijepih ulica",
        "40 zmija"
      ]
    },
    "SHORE.TR2": {
      "Names": [
        "Selo kanibala",
        "Plaža",
        "Nemoj izgubiti nogu",
        "Otrov",
        "Preskok mosta"
      ],
      "KeyItems": {
        "Key1": [
          "Podmorski ključ",
          "Jack Sparrow ključ",
          "Potopljeni ključ",
          "Zahrđali ključ",
          "Krijumčar je ovo izgubio!"
        ],
        "Puzzle1": [
          "Otrovni kamen",
          "Temple Ruins kamen",
          "Krvavi kamen",
          "Vjeruj u mene",
          "Nije konjanikov kamen"
        ]
      }
    },
    "CRASH.TR2": {
      "Names": [
        "Jurski park",
        "Dinosauri.. opet?",
        "Barney-evo mjesto",
        "Izgubljena dolina dio 2",
        "Gdje je zlatni zmaj?"
      ],
      "KeyItems": {
        "Key1": [
          "Stvorili ste Barney-a",
          "Nije Barney hrana",
          "Za što je ovo? O.o",
          "Topovski ključ",
          "Ključ destrukcije"
        ],
        "Key2": [
          "Raptor ključ",
          "Pazi leđa",
          "IZA TEBE!",
          "Neprijatelj kaže BUUU!",
          "Gdje ja stanem?"
        ]
      }
    },
    "RAPIDS.TR2": {
      "Names": [
        "Zašto ovo postoji?",
        "Potreban notepad!",
        "MADubu",
        "WC školjka",
        "Korokodili",
        "RiP korisnici slušalica"
      ]
    },
    "TRIBOSS.TR2": {
      "Names": [
        "Kanibal boss",
        "Još više otrova",
        "Footijeva tamnica",
        "Hram tune",
        "Temple Run"
      ]
    },
    "ROOFS.TR2": {
      "Names": [
        "20 sekundi",
        "Kopač na zapadu",
        "Greška u izgradnji",
        "Nema Big Bena?",
        "Zašto je ovo ovdje?",
        "London Ghetto",
        "Bruvs?"
      ],
      "KeyItems": {
        "Key1": [
          "Štakor ključ",
          "Ključ za sobu gripe",
          "Ključ za dimnjak",
          "Jednostavni ključ",
          "Zlatni ključ"
        ],
        "Key2": [
          "Predivni ključ",
          "Ključ crkve",
          "Rubin ključ",
          "Beskorisni ključ",
          "Za što je ovo? O.o"
        ]
      }
    },
    "SEWER.TR2": {
      "Names": [
        "Platforma 9 3/4",
        "Podzemlje",
        "Vožnja Londonom",
        "Ponestalo karata",
        "Pazi rupa"
      ],
      "KeyItems": {
        "Key1": [
          "Električni ključ",
          "Ključ čistača",
          "Najjači sam!",
          "Alat",
          "Popravi ovo!"
        ],
        "Key2": [
          "Pola i pola",
          "Pola",
          "Religiozni ključ",
          "Jedan ili dva?",
          "Damaklov ključ"
        ],
        "Key3": [
          "Pola i pola",
          "Jedna polovica",
          "Religiozni ključ",
          "Jedan ili dva?",
          "Damoklov ključ"
        ],
        "Key4": [
          "Pola i pola",
          "Jedna polovica",
          "Religiozni ključ",
          "Jedan ili dva?",
          "Damoklov ključ"
        ],
        "Puzzle1": [
          "NOVAC!",
          "Šiling",
          "Masivan i sjajan!",
          "Cijena voza",
          "25 bitova"
        ],
        "Puzzle2": [
          "Ajmo u Hogwarts",
          "Željeznički prolaz",
          "Nazad u Nevadu!",
          "Bez kontrole!",
          "Karta za kamenice"
        ],
        "Puzzle3": [
          "Thorov čekić",
          "Mjölnir",
          "Udari krticu",
          "Razbij lokot!",
          "Sveti Franjo čekić"
        ],
        "Puzzle4": [
          "Blistaj zvjezdo mala",
          "Sjajan sam!",
          "Vidjeli ste nešto sjajno!",
          "Ne na nebu!",
          "Jedna zvjezdica"
        ]
      }
    },
    "TOWER.TR2": {
      "Names": [
        "Muzej nacionalne povjesti",
        "Miks besmislica",
        "Ludova mržnja",
        "Ajmo mrziti",
        "Leteći UPV!"
      ],
      "KeyItems": {
        "Key1": [
          "Zagrij se!",
          "Nisi glitchao!",
          "Podmetač vatre",
          "Nema boilera?!?",
          "Hladan sam!"
        ]
      }
    },
    "OFFICE.TR2": {
      "Names": [
        "Trči Lara, TRČI!",
        "Jeli stvarno mrtva?",
        "Previše volti!",
        "Nesvjesti!",
        "Spremi i učitaj!"
      ]
    },
    "NEVADA.TR2": {
      "Names": [
        "Pustinjski orlovi",
        "Vodena pustinja",
        "Ostani hidrirani",
        "Nema pustinjskih tračnica",
        "Ovo je topla dolina!"
      ],
      "KeyItems": {
        "Key1": [
          "Generator ključ",
          "Ključ generacije",
          "JA IMAM MOĆ!",
          "Nemoj se elektrizirati!",
          "Ključ nesvjestice"
        ],
        "Key2": [
          "Ključ minskog polja",
          "TNT ključ",
          "Flipmap ključ",
          "Pristup vanzemaljcima",
          "Veliki BUM!",
          "Ključ za BOOM!"
        ]
      }
    },
    "COMPOUND.TR2": {
      "Names": [
        "Još jedan zatvor",
        "Zakon braće",
        "Veliki bijeg",
        "Boris je ovdje!",
        "Gdje mi je oružje?"
      ],
      "KeyItems": {
        "Key1": [
          "Umri čuvaru...UMRI!!",
          "Još jedna kartica",
          "MasterCard",
          "Kartica 1",
          "Kartica 2",
          "Izađi iz zatvora kartica"
        ],
        "Key2": [
          "VisaCard",
          "Kartica 1",
          "Kartica 2",
          "Tajna kartica",
          "Kreditna kartica"
        ],
        "Puzzle1": [
          "Plavi kamen",
          "Svječica 2",
          "Prekidač 2",
          "Plavi USB",
          "Nema dupliciranja"
        ],
        "Puzzle2": [
          "Žuti kamen",
          "Svjećica 1",
          "Prekidač 1",
          "Žuti USB",
          "Nema dupliciranja"
        ]
      }
    },
    "AREA51.TR2": {
      "Names": [
        "Paul je bio ovdje!",
        "Mjesto teorija zavjere",
        "Kesnomorf je bio ovdje!",
        "Dan neovisnosti",
        "Zemlja vanzemaljaca!"
      ],
      "KeyItems": {
        "Key1": [
          "Ključ rakete",
          "Ništa od vožnje raketom",
          "SpaceX ključ",
          "Raketa rakun",
          "Elon Musk ključ",
          "Možeš preskočiti i mene!",
          "Tajni brojevi",
          "Broj kreditne kartice",
          "Stvarni bacač raketi",
          "Vanzemaljci blizu?!?"
        ],
        "Puzzle1": [
          "Rapunzel ključ",
          "Visoki ključ",
          "Nije zmajev toranj",
          "Ključ za varanje",
          "VARAŠ!!!"
        ],
        "Puzzle2": [
          "Ne možeš me preskočiti!",
          "Evo mene opet!",
          "UFO disk",
          "Jedan od dva diska",
          "Muzika? O.o"
        ],
        "Puzzle3": [
          "Larin party",
          "Zagonetna muzika",
          "Jedan od dva diska",
          "Muzika džungle",
          "Možeš me preskočiti!"
        ],
        "Puzzle4": [
          "Magnetski željezni?ki klju?",
          "Klju? podzemne željeznice",
          "Klju? željezni?ke stanice",
          "Crta?a igla",
          "Slavna osoba",
          "?eki?"
        ]
      }
    },
    "ANTARC.TR2": {
      "Names": [
        "Nema pahuljica",
        "Brzi čamac 2.0",
        "Kocka leda",
        "Hod u frižideru",
        "Juha od rajčice?"
      ],
      "KeyItems": {
        "Key1": [
          "Nije paluba",
          "IceKey_Gamer",
          "Još jedan ključ",
          "Zaleđeni ključ"
        ],
        "Puzzle1": [
          "Ne zaboravi me!",
          "Bombon",
          "Štap",
          "Osjećam se snažnije!",
          "Von Štapović"
        ],
        "Puzzle2": [
          "Otvaraj rijeku",
          "Otvaraj branu",
          "Voda i voda i voda",
          "Pristup juhi",
          "Jušni ključ"
        ]
      }
    },
    "MINES.TR2": {
      "Names": [
        "Minecraft",
        "ZAŠTO?!?!?!",
        "Duboko, ledeno plivanje",
        "Stormtrooper zaljev",
        "Vatra",
        "PATI!"
      ],
      "KeyItems": {
        "Puzzle1": [
          "Ne zaboravi me!",
          "Lizalica",
          "Štap",
          "Osjećam se snažnije!",
          "Von Štapović"
        ],
        "Puzzle2": [
          "Duracell",
          "9 Volti",
          "Punjač",
          "Plava i crvena stvar",
          "Ključ dizalice!"
        ],
        "Puzzle3": [
          "Duboka zaleđena stvarčica",
          "ShawCrank iskupljenje",
          "Okretanje stvari",
          "Ozlijeđen si?",
          "Umrijet ćeš!"
        ]
      }
    },
    "CITY.TR2": {
      "Names": [
        "Skoks s mosta",
        "Život bube",
        "Pčelin film 2.0",
        "Hodnik elemenata",
        "4 načina za smrt!"
      ],
      "KeyItems": {
        "Key1": [
          "Đavolji ključ",
          "Ova cura gori!",
          "Možeš nas preskočiti!",
          "Blizanac ključ",
          "Ključ iz pakla",
          "Pogledaj me!",
          "Kolačić ključ"
        ],
        "Puzzle1": [
          "Maska za lice",
          "Nije Golden Mask",
          "Fantom iz opere",
          "Masikrana kugla dolazi",
          "MASKA"
        ]
      }
    },
    "CHAMBER.TR2": {
      "Names": [
        "Inči vinči pauk",
        "20 - 40 orlova",
        "Japanski preporučen",
        "Oslobodi Vilija",
        "Willardova paučina"
      ]
    },
    "STPAUL.TR2": {
      "Names": [
        "Ovo je tajna",
        "60/59",
        "Nedovršeni posao",
        "Smrtonosna katedrala",
        "Bez štete"
      ],
      "KeyItems": {
        "Key1": [
          "Super skriven",
          "Ljestve na zidu",
          "Pronašao si me konačno?",
          "Igra skrivača",
          "Ptičja gripa"
        ]
      }
    }
  }
}