{
  "VariantMap": {
    "Blue": [
      "0, 0, 64, 64",
      "0, 64, 24, 24"
    ],
    "Jade": [
      "64, 0, 64, 64",
      "64, 64, 24, 24"
    ],
    "Orange": [
      "128, 0, 64, 64",
      "128, 64, 24, 24"
    ],
    "Red": [
      "192, 0, 64, 64",
      "192, 64, 24, 24"
    ],
    "Silver": [
      "256, 0, 64, 64",
      "256, 64, 24, 24"
    ],
    "Purple": [
      "320, 0, 64, 64",
      "320, 64, 24, 24"
    ],
    "Zen": [
      "384, 0, 64, 64",
      "384, 64, 24, 24"
    ],
    "Lilly": [
      "448, 0, 64, 64",
      "448, 64, 24, 24"
    ]
  }
}