{
  "Dynamic": {
    "Tibet.SnowTheme": {
      "ObjectTextureIndices": [ 940, 944, 945, 946, 947, 948, 950, 956, 959, 966, 967, 968, 969, 970, 972, 973, 974, 975, 976, 1175, 1176, 1177, 1181, 1182, 1183, 1185, 1186, 1187, 1188, 1190, 1191, 1192, 1193, 1194, 1195, 1196, 1197, 1198, 1199, 1237, 1238, 1239, 1241, 1243, 1246, 1248, 1250, 1251, 1253, 1254, 1256, 1258, 1259, 1260, 1261, 1262, 1263, 1265, 1267, 1268, 1269, 1271, 1274, 1276, 1277, 1280, 1282, 1283, 1284, 1286, 1287, 1288, 1289, 1290, 1293, 1294, 1296, 1297, 1298, 1299, 1300, 1301, 1302, 1303, 1304, 1305, 1306, 1307, 1308, 1309, 1310, 1311, 1312, 1313, 1314, 1317, 1321, 1323, 1324, 1325, 1326, 1329, 1332, 1333, 1336, 1337, 1341, 1342, 1343, 1344, 1346, 1350, 1351, 1353, 1354, 1355, 1356, 1358, 1359, 1360, 1364, 1365, 1369, 1373, 1374, 1375, 1376, 1381, 1383, 1388, 1389, 1391, 1394, 1399, 1402, 1403, 1405, 1408, 1409, 1411, 1412, 1419, 1420, 1421, 1423, 1424, 1431, 1439, 1446, 1447, 1448, 1449, 1454, 1464, 1466, 1479, 1480, 1493, 1501, 1502, 1503, 1512, 1544, 1546, 1549, 1560, 1566, 1572, 1573, 1574, 1578, 1581, 1587, 1598, 1599, 1600, 1603, 1604, 1605, 1608, 1611, 1622, 1623, 1625, 1663, 1678, 1683, 1685, 1686, 1693, 1703, 1707, 1710, 1711, 1718, 1720, 1744, 1779, 1780 ],
      "SpriteTextureIndices": [ 24, 25, 30, 31, 32, 33 ]
    }
  },

  "Static": {
    "Enemies.Monks": [
      {
        "Segment": 0,
        "Tile": 9,
        "X": 144,
        "Y": 192
      },
      {
        "Segment": 1,
        "Tile": 9,
        "X": 208,
        "Y": 200
      },
      {
        "Segment": 2,
        "Tile": 10,
        "X": 128,
        "Y": 0
      },
      {
        "Segment": 3,
        "Tile": 10,
        "X": 160,
        "Y": 0
      },
      {
        "Segment": 4,
        "Tile": 10,
        "X": 192,
        "Y": 0
      },
      {
        "Segment": 5,
        "Tile": 11,
        "X": 0,
        "Y": 128
      },
      {
        "Segment": 6,
        "Tile": 10,
        "X": 224,
        "Y": 0
      },
      {
        "Segment": 7,
        "Tile": 13,
        "X": 48,
        "Y": 176
      },
      {
        "Segment": 8,
        "Tile": 13,
        "X": 80,
        "Y": 176
      },
      {
        "Segment": 9,
        "Tile": 11,
        "X": 24,
        "Y": 0
      },
      {
        "Segment": 9,
        "Tile": 13,
        "X": 96,
        "Y": 32,
        "Clip": "0, 24, 24, 16"
      },
      {
        "Segment": 10,
        "Tile": 11,
        "X": 48,
        "Y": 0
      },
      {
        "Segment": 10,
        "Tile": 13,
        "X": 144,
        "Y": 48,
        "Clip": "0, 24, 24, 16"
      },
      {
        "Segment": 11,
        "Tile": 11,
        "X": 96,
        "Y": 144
      },
      {
        "Segment": 12,
        "Tile": 11,
        "X": 64,
        "Y": 144
      },
      {
        "Segment": 13,
        "Tile": 13,
        "X": 160,
        "Y": 144
      },
      {
        "Segment": 14,
        "Tile": 13,
        "X": 16,
        "Y": 152
      },
      {
        "Segment": 15,
        "Tile": 11,
        "X": 128,
        "Y": 144
      },
      {
        "Segment": 16,
        "Tile": 11,
        "X": 152,
        "Y": 144
      },
      {
        "Segment": 17,
        "Tile": 11,
        "X": 128,
        "Y": 128
      },
      {
        "Segment": 17,
        "Tile": 11,
        "X": 152,
        "Y": 128
      },
      {
        "Segment": 18,
        "Tile": 13,
        "X": 72,
        "Y": 32
      },
      {
        "Segment": 18,
        "Tile": 13,
        "X": 72,
        "Y": 48
      },
      {
        "Segment": 19,
        "Tile": 11,
        "X": 240,
        "Y": 0
      },
      {
        "Segment": 19,
        "Tile": 13,
        "X": 32,
        "Y": 152,
        "Clip": "0, 32, 16, 16"
      },
      {
        "Segment": 19,
        "Tile": 13,
        "X": 144,
        "Y": 144,
        "Clip": "0, 0, 16, 16"
      },
      {
        "Segment": 20,
        "Tile": 11,
        "X": 240,
        "Y": 88
      },
      {
        "Segment": 20,
        "Tile": 13,
        "X": 112,
        "Y": 176,
        "Clip": "0, 32, 16, 16"
      },
      {
        "Segment": 20,
        "Tile": 13,
        "X": 0,
        "Y": 176,
        "Clip": "0, 0, 16, 16"
      },
      {
        "Segment": 21,
        "Tile": 13,
        "X": 168,
        "Y": 32
      },
      {
        "Segment": 22,
        "Tile": 13,
        "X": 168,
        "Y": 48
      },
      {
        "Segment": 23,
        "Tile": 13,
        "X": 96,
        "Y": 168
      },
      {
        "Segment": 24,
        "Tile": 11,
        "X": 248,
        "Y": 48
      },
      {
        "Segment": 25,
        "Tile": 12,
        "X": 248,
        "Y": 0
      },
      {
        "Segment": 26,
        "Tile": 13,
        "X": 16,
        "Y": 184
      },
      {
        "Segment": 26,
        "Tile": 13,
        "X": 192,
        "Y": 184
      },
      {
        "Segment": 27,
        "Tile": 13,
        "X": 232,
        "Y": 40
      },
      {
        "Segment": 28,
        "Tile": 13,
        "X": 48,
        "Y": 168
      }
    ],

    "Flame": [
      {
        "Segment": 0,
        "Tile": 6,
        "X": 4,
        "Y": 66
      },
      {
        "Segment": 1,
        "Tile": 6,
        "X": 132,
        "Y": 2
      },
      {
        "Segment": 2,
        "Tile": 14,
        "X": 161,
        "Y": 40
      },
      {
        "Segment": 3,
        "Tile": 14,
        "X": 2,
        "Y": 81
      },
      {
        "Segment": 4,
        "Tile": 6,
        "X": 145,
        "Y": 68
      },
      {
        "Segment": 5,
        "Tile": 6,
        "X": 1,
        "Y": 128
      },
      {
        "Segment": 6,
        "Tile": 6,
        "X": 146,
        "Y": 130
      },
      {
        "Segment": 7,
        "Tile": 6,
        "X": 0,
        "Y": 184
      },
      {
        "Segment": 8,
        "Tile": 6,
        "X": 160,
        "Y": 184
      },
      {
        "Segment": 9,
        "Tile": 14,
        "X": 169,
        "Y": 93
      },
      {
        "Segment": 10,
        "Tile": 14,
        "X": 2,
        "Y": 160
      },
      {
        "Segment": 11,
        "Tile": 14,
        "X": 68,
        "Y": 169
      },
      {
        "Segment": 12,
        "Tile": 15,
        "X": 90,
        "Y": 46
      },
      {
        "Segment": 13,
        "Tile": 14,
        "X": 200,
        "Y": 217
      },
      {
        "Segment": 14,
        "Tile": 6,
        "X": 226,
        "Y": 134
      },
      {
        "Segment": 15,
        "Tile": 15,
        "X": 232,
        "Y": 60
      },
      {
        "Segment": 16,
        "Tile": 15,
        "X": 203,
        "Y": 84
      },
      {
        "Segment": 17,
        "Tile": 15,
        "X": 123,
        "Y": 89
      },
      {
        "Segment": 18,
        "Tile": 15,
        "X": 228,
        "Y": 105
      },
      {
        "Segment": 19,
        "Tile": 15,
        "X": 44,
        "Y": 105
      }
    ],

    "Lara.Bobble": [
      {
        "Segment": 0,
        "Tile": 12,
        "X": 40,
        "Y": 235
      },
      {
        "Segment": 1,
        "Tile": 13,
        "X": 240,
        "Y": 81
      }
    ],

    "Lara.Socks": [
      {
        "Segment": 0,
        "Tile": 9,
        "X": 240,
        "Y": 136
      },
      {
        "Segment": 1,
        "Tile": 12,
        "X": 240,
        "Y": 48
      },
      {
        "Segment": 2,
        "Tile": 12,
        "X": 240,
        "Y": 80
      }
    ],

    "Lara.Top.Snow": [
      {
        "Segment": 0,
        "Tile": 11,
        "X": 208,
        "Y": 0
      },
      {
        "Segment": 1,
        "Tile": 9,
        "X": 240,
        "Y": 200,
        "Clip": "0, 0, 16, 56"
      },
      {
        "Segment": 1,
        "Tile": 10,
        "X": 240,
        "Y": 160,
        "Clip": "16, 0, 16, 56"
      },
      {
        "Segment": 2,
        "Tile": 12,
        "X": 160,
        "Y": 208,
        "Clip": "0, 0, 16, 24"
      },
      {
        "Segment": 2,
        "Tile": 12,
        "X": 192,
        "Y": 208,
        "Clip": "16, 0, 16, 24"
      },
      {
        "Segment": 3,
        "Tile": 11,
        "X": 96,
        "Y": 64
      },
      {
        "Segment": 4,
        "Tile": 12,
        "X": 32,
        "Y": 0
      },
      {
        "Segment": 5,
        "Tile": 12,
        "X": 56,
        "Y": 0
      },
      {
        "Segment": 6,
        "Tile": 12,
        "X": 232,
        "Y": 192
      },
      {
        "Segment": 7,
        "Tile": 9,
        "X": 200,
        "Y": 128
      },
      {
        "Segment": 8,
        "Tile": 12,
        "X": 152,
        "Y": 0
      },
      {
        "Segment": 9,
        "Tile": 12,
        "X": 128,
        "Y": 0
      },
      {
        "Segment": 10,
        "Tile": 12,
        "X": 24,
        "Y": 192
      },
      {
        "Segment": 11,
        "Tile": 11,
        "X": 64,
        "Y": 168
      },
      {
        "Segment": 12,
        "Tile": 12,
        "X": 176,
        "Y": 0
      },
      {
        "Segment": 13,
        "Tile": 11,
        "X": 128,
        "Y": 176
      },
      {
        "Segment": 14,
        "Tile": 12,
        "X": 208,
        "Y": 208
      }
    ],

    "Lara.Top.Sun": [
      {
        "Segment": 0,
        "Tile": 9,
        "X": 147,
        "Y": 128
      },
      {
        "Segment": 2,
        "Tile": 9,
        "X": 176,
        "Y": 152,
        "Clip": "0, 0, 24, 16"
      },
      {
        "Segment": 6,
        "Tile": 12,
        "X": 24,
        "Y": 40
      },
      {
        "Segment": 19,
        "Tile": 12,
        "X": 80,
        "Y": 16,
        "Clip": "8, 0, 24, 8"
      },
      {
        "Segment": 25,
        "Tile": 10,
        "X": 122,
        "Y": 240
      }
    ],

    "Skybox": "#5898B8",

    "Tibet.Sky": [
      {
        "Segment": 1,
        "Tile": 7,
        "X": 192,
        "Y": 192
      },
      {
        "Segment": 2,
        "Tile": 8,
        "X": 0,
        "Y": 0
      },
      {
        "Segment": 3,
        "Tile": 8,
        "X": 64,
        "Y": 0
      },
      {
        "Segment": 4,
        "Tile": 8,
        "X": 128,
        "Y": 0
      }
    ]
  }
}